pins/__init__.py
pins/_adaptors.py
pins/_types.py
pins/boards.py
pins/cache.py
pins/config.py
pins/constructors.py
pins/drivers.py
pins/errors.py
pins/meta.py
pins/utils.py
pins/versions.py
pins/data/__init__.py
pins/data/mtcars.csv
pins/databricks/__init__.py
pins/databricks/fs.py
pins/rsconnect/__init__.py
pins/rsconnect/api.py
pins/rsconnect/fs.py
pins/rsconnect/html/index.html
pins/rsconnect/html/highlight.js-9.15.9/highlight.js
pins/rsconnect/html/highlight.js-9.15.9/qtcreator_light.css
pins/rsconnect/html/pagedtable-1.1/pagedtable.css
pins/rsconnect/html/pagedtable-1.1/pagedtable.js
pins/tests/.gitignore
pins/tests/conftest.py
pins/tests/helpers.py
pins/tests/test_adaptors.py
pins/tests/test_boards.py
pins/tests/test_cache.py
pins/tests/test_compat.py
pins/tests/test_compat_old_types.py
pins/tests/test_config.py
pins/tests/test_constructors.py
pins/tests/test_drivers.py
pins/tests/test_meta.py
pins/tests/test_rsconnect_api.py
pins/tests/test_utils.py
pins/tests/test_versions.py
pins/tests/_snapshots/test_board_pin_write_rsc_index_html/data.txt
pins/tests/_snapshots/test_board_pin_write_rsc_index_html/index.html
pins/tests/_snapshots/test_board_pin_write_rsc_index_html/test_rsc_pin.csv
pins/tests/_snapshots/test_board_pin_write_rsc_index_html/highlight.js-9.15.9/highlight.js
pins/tests/_snapshots/test_board_pin_write_rsc_index_html/highlight.js-9.15.9/qtcreator_light.css
pins/tests/_snapshots/test_board_pin_write_rsc_index_html/pagedtable-1.1/pagedtable.css
pins/tests/_snapshots/test_board_pin_write_rsc_index_html/pagedtable-1.1/pagedtable.js
pins/tests/example-bundle/data.txt
pins/tests/example-bundle/data_frame.csv
pins/tests/example-bundle/index.html
pins/tests/example-bundle/manifest.json
pins/tests/pin-board/_pins.yaml
pins/tests/pin-board/x/20221215T180351Z-c3943/data.txt
pins/tests/pin-board/x/20221215T180351Z-c3943/x.json
pins/tests/pin-board/y/20221215T180357Z-9ae7a/data.txt
pins/tests/pin-board/y/20221215T180357Z-9ae7a/y.rds
pins-0.9.1.dist-info/licenses/LICENSE
pins-0.9.1.dist-info/METADATA
pins-0.9.1.dist-info/WHEEL
pins-0.9.1.dist-info/top_level.txt
pins-0.9.1.dist-info/RECORD
