Metadata-Version: 2.4
Name: pins
Version: 0.9.1
Summary: Publish data sets, models, and other python objects, making it easy to share them across projects and with your colleagues.
Author-email: Michael Chow <michael.chow@posit.co>
Maintainer-email: Isabel Zimmerman <isabel.zimmerman@posit.co>
Project-URL: Documentation, https://rstudio.github.io/pins-python
Project-URL: Homepage, https://github.com/rstudio/pins-python
Keywords: data,tidyverse
Classifier: Programming Language :: Python :: 3 :: Only
Classifier: Programming Language :: Python :: 3.9
Classifier: Programming Language :: Python :: 3.10
Classifier: Programming Language :: Python :: 3.11
Classifier: Programming Language :: Python :: 3.12
Classifier: Programming Language :: Python :: 3.13
Classifier: License :: OSI Approved :: MIT License
Requires-Python: >=3.9
License-File: LICENSE
Requires-Dist: appdirs<2
Requires-Dist: fsspec<2025.9,>=2022.2
Requires-Dist: humanize>=1
Requires-Dist: importlib-metadata>=4.4
Requires-Dist: importlib-resources>=1.3
Requires-Dist: jinja2>=2.10
Requires-Dist: joblib>=0.12
Requires-Dist: pandas>=0.23
Requires-Dist: pyyaml>=3.13
Requires-Dist: requests
Requires-Dist: xxhash>=1
Requires-Dist: databackend>=0.0.3
Requires-Dist: typing_extensions
Provides-Extra: aws
Requires-Dist: s3fs; extra == "aws"
Provides-Extra: azure
Requires-Dist: adlfs>=2024.4.1; extra == "azure"
Provides-Extra: check
Requires-Dist: pre-commit; extra == "check"
Requires-Dist: pyright==1.1.372; extra == "check"
Requires-Dist: ruff==0.5.4; extra == "check"
Requires-Dist: types-appdirs; extra == "check"
Requires-Dist: pins[databricks]; extra == "check"
Provides-Extra: databricks
Requires-Dist: databricks-sdk; extra == "databricks"
Provides-Extra: doc
Requires-Dist: ipykernel; extra == "doc"
Requires-Dist: ipython<=8.12; extra == "doc"
Requires-Dist: nbclient; extra == "doc"
Requires-Dist: nbformat; extra == "doc"
Requires-Dist: quartodoc; extra == "doc"
Provides-Extra: gcs
Requires-Dist: gcsfs; extra == "gcs"
Provides-Extra: test
Requires-Dist: pins[azure]; extra == "test"
Requires-Dist: pins[gcs]; extra == "test"
Requires-Dist: pins[databricks]; extra == "test"
Requires-Dist: pins[aws]; extra == "test"
Requires-Dist: fastparquet; extra == "test"
Requires-Dist: pip-tools; extra == "test"
Requires-Dist: pyarrow; extra == "test"
Requires-Dist: pytest==7.1.3; extra == "test"
Requires-Dist: pytest-cases; extra == "test"
Requires-Dist: pytest-dotenv; extra == "test"
Requires-Dist: pytest-parallel; extra == "test"
Requires-Dist: rdata; extra == "test"
Dynamic: license-file
